mpyconfigbase/__init__.py
mpyconfigbase/mpyconfigbase.py
mpyconfigbase/sample.py
mpyconfigbase-0.0.4.dist-info/LICENSE
mpyconfigbase-0.0.4.dist-info/METADATA
mpyconfigbase-0.0.4.dist-info/WHEEL
mpyconfigbase-0.0.4.dist-info/top_level.txt
mpyconfigbase-0.0.4.dist-info/RECORD
