Metadata-Version: 2.1
Name: mpyconfigbase
Version: 0.0.4
Summary: Configure MicroPython WLAN/AP/WebRepl startup with your own code
Home-page: https://github.com/kr-g/mpyconfigbase
Author: k.r. goger
Author-email: k.r.goger+mpyconfigbase@gmail.com
License: MIT
Keywords: micropython utility shell automation deployment
Platform: UNKNOWN
Classifier: Development Status :: 3 - Alpha
Classifier: Operating System :: POSIX :: Linux
Classifier: Environment :: Console
Classifier: Intended Audience :: Developers
Classifier: Topic :: Software Development :: Embedded Systems
Classifier: Topic :: Terminals :: Serial
Classifier: Topic :: Utilities
Classifier: Programming Language :: Python :: 3
Classifier: License :: OSI Approved :: MIT License
Requires-Python: >=3.6
Requires-Dist: mpycntrl
